{"lessonId":"710","lessonName":"[IPA] - /tʃ/ - /ʃ/ (cheap vs sheep)","audioSrc":"","challenges":[{"id":33253,"position":1,"content":"","jsonContent":[""],"solution":[[""]],"audioSrc":""},{"id":33255,"position":2,"content":"","jsonContent":[""],"solution":[[""]],"audioSrc":""},{"id":33257,"position":3,"content":"","jsonContent":[""],"solution":[[""]],"audioSrc":""},{"id":33259,"position":4,"content":"","jsonContent":[""],"solution":[[""]],"audioSrc":""},{"id":33262,"position":5,"content":"","jsonContent":[""],"solution":[[""]],"audioSrc":""},{"id":33264,"position":6,"content":"","jsonContent":[""],"solution":[[""]],"audioSrc":""},{"id":33266,"position":7,"content":"","jsonContent":[""],"solution":[[""]],"audioSrc":""},{"id":33268,"position":8,"content":"","jsonContent":[""],"solution":[[""]],"audioSrc":""},{"id":33270,"position":9,"content":"","jsonContent":[""],"solution":[[""]],"audioSrc":""},{"id":33272,"position":10,"content":"","jsonContent":[""],"solution":[[""]],"audioSrc":""}]}